indexed_pq/__init__.py
indexed_pq/ipq.py
indexed_pq-0.1.3.dist-info/METADATA
indexed_pq-0.1.3.dist-info/WHEEL
indexed_pq-0.1.3.dist-info/top_level.txt
indexed_pq-0.1.3.dist-info/RECORD
