Metadata-Version: 2.1
Name: indexed-pq
Version: 0.1.3
Summary: UNKNOWN
Home-page: UNKNOWN
Author: humblemat
Author-email: humblemat@gmail.com
License: MIT
Platform: UNKNOWN
Classifier: Programming Language :: Python :: 3
Classifier: License :: OSI Approved :: MIT License
Classifier: Operating System :: OS Independent
